ion/__init__.py
ion/_core.py
ion/py.typed
bolton_ion-0.1.0.dist-info/METADATA
bolton_ion-0.1.0.dist-info/WHEEL
bolton_ion-0.1.0.dist-info/top_level.txt
bolton_ion-0.1.0.dist-info/RECORD
